pylexirumah/__init__.py
pylexirumah/align.py
pylexirumah/append_changed_cognate_classes.py
pylexirumah/autocode.py
pylexirumah/autocode_cldf.py
pylexirumah/cldf.py
pylexirumah/clld_sqlite.py
pylexirumah/create_glottolog_skeleton.py
pylexirumah/geo_lookup.py
pylexirumah/import_keraf_data.py
pylexirumah/lingpycldf.py
pylexirumah/plot_parameters.py
pylexirumah/segment.py
pylexirumah/util.py
pylexirumah-0.3.dist-info/DESCRIPTION.rst
pylexirumah-0.3.dist-info/METADATA
pylexirumah-0.3.dist-info/RECORD
pylexirumah-0.3.dist-info/WHEEL
pylexirumah-0.3.dist-info/entry_points.txt
pylexirumah-0.3.dist-info/metadata.json
pylexirumah-0.3.dist-info/top_level.txt
tests/__init__.py
tests/test_segment.py
