Metadata-Version: 2.0
Name: pylexirumah
Version: 0.3
Summary: programmatic access to lexirumah-data
Home-page: UNKNOWN
Author: Gereon A. Kaiping
Author-email: g.a.kaiping@hum.leidenuniv.nl
License: UNKNOWN
Keywords: data linguistics
Platform: UNKNOWN
Classifier: Programming Language :: Python
Classifier: Programming Language :: Python :: 2.7
Classifier: Programming Language :: Python :: 3
Classifier: Programming Language :: Python :: 3.4
Requires-Dist: clldutils
Requires-Dist: pycldf
Requires-Dist: pyclpa
